oxidize_xml-0.1.0.dist-info/METADATA
oxidize_xml-0.1.0.dist-info/WHEEL
oxidize_xml/__init__.py
oxidize_xml/oxidize_xml.cpython-312-darwin.so
oxidize_xml-0.1.0.dist-info/RECORD
