Metadata-Version: 2.4
Name: oxidize-xml
Version: 0.1.0
Classifier: Development Status :: 4 - Beta
Classifier: Intended Audience :: Developers
Classifier: Programming Language :: Python :: 3
Classifier: Programming Language :: Python :: 3.9
Classifier: Programming Language :: Python :: 3.10
Classifier: Programming Language :: Python :: 3.11
Classifier: Programming Language :: Python :: 3.12
Classifier: Programming Language :: Rust
Classifier: Topic :: Software Development :: Libraries :: Python Modules
Classifier: Topic :: Text Processing :: Markup :: XML
Summary: High-performance XML to JSON streaming parser built with Rust
Keywords: xml,json,parser,rust,performance,streaming
Author: Eric Aleman
Requires-Python: >=3.9
Project-URL: Repository, https://github.com/ericaleman/oxidize-xml
